test_pack_PAN/__init__.py
test_pack_PAN/testing.py
test_pack_PAN-1.0.dist-info/LICENSE.txt
test_pack_PAN-1.0.dist-info/METADATA
test_pack_PAN-1.0.dist-info/WHEEL
test_pack_PAN-1.0.dist-info/top_level.txt
test_pack_PAN-1.0.dist-info/RECORD
